odoo/addons/repair_security/README.rst
odoo/addons/repair_security/__init__.py
odoo/addons/repair_security/__manifest__.py
odoo/addons/repair_security/hook.py
odoo/addons/repair_security/i18n/it.po
odoo/addons/repair_security/i18n/repair_security.pot
odoo/addons/repair_security/readme/CONTRIBUTORS.md
odoo/addons/repair_security/readme/DESCRIPTION.md
odoo/addons/repair_security/security/ir.model.access.csv
odoo/addons/repair_security/security/repair_security.xml
odoo/addons/repair_security/static/description/icon.png
odoo/addons/repair_security/static/description/index.html
odoo/addons/repair_security/views/repair_views.xml
odoo_addon_repair_security-19.0.1.0.0.4.dist-info/METADATA
odoo_addon_repair_security-19.0.1.0.0.4.dist-info/WHEEL
odoo_addon_repair_security-19.0.1.0.0.4.dist-info/top_level.txt
odoo_addon_repair_security-19.0.1.0.0.4.dist-info/RECORD
