Metadata-Version: 2.1
Name: odoo-addon-repair_security
Version: 19.0.1.0.0.4
Requires-Dist: odoo==19.0.*
Summary: Create security groups for Repair
Home-page: https://github.com/OCA/repair
License: AGPL-3
Author: ForgeFlow S.L., Odoo Community Association (OCA)
Author-email: support@odoo-community.org
Classifier: Programming Language :: Python
Classifier: Framework :: Odoo
Classifier: Framework :: Odoo :: 19.0
Classifier: License :: OSI Approved :: GNU Affero General Public License v3
